README.md
setup.cfg
setup.py
octant/__init__.py
octant/core.py
octant/decor.py
octant/exceptions.py
octant/misc.py
octant/plotting.py
octant/utils.pyx
octant/version.py
octant.egg-info/PKG-INFO
octant.egg-info/SOURCES.txt
octant.egg-info/dependency_links.txt
octant.egg-info/not-zip-safe
octant.egg-info/requires.txt
octant.egg-info/top_level.txt