Metadata-Version: 1.1
Name: octant
Version: 0.0.13
Summary: Objective Cyclone Tracking ANalysis Tools
Home-page: https://github.com/dennissergeev/octant
Author: Denis Sergeev
Author-email: dennis.sergeev@gmail.com
License: UNKNOWN
Platform: UNKNOWN
Classifier: Intended Audience :: Science/Research
Classifier: License :: OSI Approved :: MIT License
Classifier: Operating System :: POSIX :: Linux
Classifier: Programming Language :: Python :: 3.6
Classifier: Topic :: Scientific/Engineering :: Atmospheric Science
